auto_commit/__init__.py
auto_commit/__main__.py
auto_commit/cli/__init__.py
auto_commit/cli/commands.py
auto_commit/core/__init__.py
auto_commit-0.1.0.dist-info/entry_points.txt
auto_commit-0.1.0.dist-info/WHEEL
auto_commit-0.1.0.dist-info/METADATA
auto_commit-0.1.0.dist-info/RECORD
