Metadata-Version: 2.1
Name: auto-commit
Version: 0.1.0
Summary: Make automatically git commits when coding
License: MIT
Author: duyixian
Author-email: duyixian1234@qq.com
Requires-Python: >=3.8,<4.0
Classifier: License :: OSI Approved :: MIT License
Classifier: Programming Language :: Python :: 3
Classifier: Programming Language :: Python :: 3.8
Classifier: Programming Language :: Python :: 3.9
Requires-Dist: typer (>=0.3.2,<0.4.0)
